aerosandbox/README.md
aerosandbox/__init__.py
aerosandbox/common.py
aerosandbox/aerodynamics/__init__.py
aerosandbox/aerodynamics/aero_2D/IBL2.py
aerosandbox/aerodynamics/aero_2D/__init__.py
aerosandbox/aerodynamics/aero_2D/airfoil_inviscid.py
aerosandbox/aerodynamics/aero_2D/airfoil_polar_functions.py
aerosandbox/aerodynamics/aero_2D/mses.py
aerosandbox/aerodynamics/aero_2D/xfoil.py
aerosandbox/aerodynamics/aero_2D/airfoil_optimizer/README.md
aerosandbox/aerodynamics/aero_2D/airfoil_optimizer/__init__.py
aerosandbox/aerodynamics/aero_2D/airfoil_optimizer/airfoil_optimizer.py
aerosandbox/aerodynamics/aero_2D/in_progress/viscous analysis.py
aerosandbox/aerodynamics/aero_2D/singularities/__init__.py
aerosandbox/aerodynamics/aero_2D/singularities/linear_strength_line_singularities.py
aerosandbox/aerodynamics/aero_2D/singularities/test_singularities/test_linear_vortex_strength.py
aerosandbox/aerodynamics/aero_2D/test_aero_2D/test_airfoil_inviscid.py
aerosandbox/aerodynamics/aero_3D/README.md
aerosandbox/aerodynamics/aero_3D/__init__.py
aerosandbox/aerodynamics/aero_3D/aero_buildup.py
aerosandbox/aerodynamics/aero_3D/avl.py
aerosandbox/aerodynamics/aero_3D/lifting_line.py
aerosandbox/aerodynamics/aero_3D/vortex_lattice_method.py
aerosandbox/aerodynamics/aero_3D/aero_buildup_submodels/fuselage_aerodynamics_utilities.py
aerosandbox/aerodynamics/aero_3D/singularities/__init__.py
aerosandbox/aerodynamics/aero_3D/singularities/point_source.py
aerosandbox/aerodynamics/aero_3D/singularities/uniform_strength_horseshoe_singularities.py
aerosandbox/aerodynamics/aero_3D/test_aero_3D/test_avl.py
aerosandbox/aerodynamics/aero_3D/test_aero_3D/test_lifting_line.py
aerosandbox/aerodynamics/aero_3D/test_aero_3D/test_vortex_lattice_method.py
aerosandbox/aerodynamics/aero_3D/test_aero_3D/geometries/__init__.py
aerosandbox/aerodynamics/aero_3D/test_aero_3D/geometries/conventional.py
aerosandbox/aerodynamics/aero_3D/test_aero_3D/geometries/flat_plate.py
AeroSandbox-3.5.11.dist-info/LICENSE.txt
AeroSandbox-3.5.11.dist-info/METADATA
AeroSandbox-3.5.11.dist-info/WHEEL
AeroSandbox-3.5.11.dist-info/top_level.txt
AeroSandbox-3.5.11.dist-info/RECORD
