Metadata-Version: 2.1
Name: AeroSandbox
Version: 3.5.11
Summary: A Python 3 package for playing around with aerodynamics ideas related to vortex lattice methods, coupled viscous/inviscid methods, automatic differentiation for gradient computation, aircraft design optimization, and the like. Work in progress!
Home-page: https://peterdsharpe.github.io/AeroSandbox/
Author: Peter Sharpe
Author-email: pds@mit.edu
Project-URL: Source, https://github.com/peterdsharpe/AeroSandbox
Project-URL: Bug Reports, https://github.com/peterdsharpe/AeroSandbox/issues
Keywords: aerodynamics airplane cfd mdo mdao aircraft design aerospace optimization automatic differentiation
Classifier: Development Status :: 4 - Beta
Classifier: Intended Audience :: Science/Research
Classifier: Topic :: Scientific/Engineering :: Physics
Classifier: License :: OSI Approved :: MIT License
Classifier: Programming Language :: Python
Requires-Python: >=3.6
License-File: LICENSE.txt
Requires-Dist: numpy (>=1.20.0)
Requires-Dist: scipy (>=1.7.0)
Requires-Dist: casadi (>=3.5.5)
Requires-Dist: pandas (>=1)
Requires-Dist: matplotlib (>=3.3.1)
Requires-Dist: seaborn (>=0.11)
Requires-Dist: tqdm (>=4)
Requires-Dist: sortedcontainers (>2)
Provides-Extra: full
Requires-Dist: plotly (>=5) ; extra == 'full'
Requires-Dist: pyvista (>=0.31) ; extra == 'full'
Requires-Dist: ipyvtklink (>=0.2) ; extra == 'full'
Requires-Dist: trimesh (>=3) ; extra == 'full'
Requires-Dist: sympy (>=1) ; extra == 'full'
Provides-Extra: test
Requires-Dist: pytest ; extra == 'test'
Requires-Dist: nbval ; extra == 'test'
